LICENSE
README.md
setup.py
StreamingWavelet/MakeCDJVFilter.py
StreamingWavelet/StreamingWavelet.py
StreamingWavelet/__init__.py
StreamingWavelet.egg-info/PKG-INFO
StreamingWavelet.egg-info/SOURCES.txt
StreamingWavelet.egg-info/dependency_links.txt
StreamingWavelet.egg-info/requires.txt
StreamingWavelet.egg-info/top_level.txt
StreamingWavelet/wavelets_coeff/__init__.py
StreamingWavelet/wavelets_coeff/bior1_1.py
StreamingWavelet/wavelets_coeff/bior1_3.py
StreamingWavelet/wavelets_coeff/bior1_5.py
StreamingWavelet/wavelets_coeff/bior2_2.py
StreamingWavelet/wavelets_coeff/bior2_4.py
StreamingWavelet/wavelets_coeff/bior2_6.py
StreamingWavelet/wavelets_coeff/bior2_8.py
StreamingWavelet/wavelets_coeff/bior3_1.py
StreamingWavelet/wavelets_coeff/bior3_3.py
StreamingWavelet/wavelets_coeff/bior3_5.py
StreamingWavelet/wavelets_coeff/bior3_7.py
StreamingWavelet/wavelets_coeff/bior3_9.py
StreamingWavelet/wavelets_coeff/bior4_4.py
StreamingWavelet/wavelets_coeff/bior5_5.py
StreamingWavelet/wavelets_coeff/bior6_8.py
StreamingWavelet/wavelets_coeff/coif1.py
StreamingWavelet/wavelets_coeff/coif2.py
StreamingWavelet/wavelets_coeff/coif3.py
StreamingWavelet/wavelets_coeff/coif4.py
StreamingWavelet/wavelets_coeff/coif5.py
StreamingWavelet/wavelets_coeff/db10.py
StreamingWavelet/wavelets_coeff/db11.py
StreamingWavelet/wavelets_coeff/db12.py
StreamingWavelet/wavelets_coeff/db13.py
StreamingWavelet/wavelets_coeff/db14.py
StreamingWavelet/wavelets_coeff/db15.py
StreamingWavelet/wavelets_coeff/db16.py
StreamingWavelet/wavelets_coeff/db17.py
StreamingWavelet/wavelets_coeff/db18.py
StreamingWavelet/wavelets_coeff/db19.py
StreamingWavelet/wavelets_coeff/db2.py
StreamingWavelet/wavelets_coeff/db20.py
StreamingWavelet/wavelets_coeff/db3.py
StreamingWavelet/wavelets_coeff/db4.py
StreamingWavelet/wavelets_coeff/db5.py
StreamingWavelet/wavelets_coeff/db6.py
StreamingWavelet/wavelets_coeff/db7.py
StreamingWavelet/wavelets_coeff/db8.py
StreamingWavelet/wavelets_coeff/db9.py
StreamingWavelet/wavelets_coeff/dmey.py
StreamingWavelet/wavelets_coeff/haar.py
StreamingWavelet/wavelets_coeff/sym10.py
StreamingWavelet/wavelets_coeff/sym11.py
StreamingWavelet/wavelets_coeff/sym12.py
