Metadata-Version: 2.1
Name: StreamingWavelet
Version: 1.0.5
Summary: This is an implementation for Streaming Wavelet Operator, which sequentially apply wavelet transform to a sequence efficiently. Reference: Qian et al., Efficient Non-stationary Online Learning by Wavelets with Applications to Online Distribution Shift Adaptation. In Proceedings of the 41st International Conference on Machine Learning (ICML 2024).
Home-page: https://github.com/ZinYY/StreamingWavelet
Author: Yu-Yang Qian
Author-email: qianyy@lamda.nju.edu.cn
License: MIT
Platform: any
Classifier: Programming Language :: Python :: 3
Classifier: License :: OSI Approved :: MIT License
Classifier: Operating System :: OS Independent
License-File: LICENSE
